vdb_schema/__init__.py
vdb_schema/actor.py
vdb_schema/category.py
vdb_schema/content.py
vdb_schema/content_bundle.py
vdb_schema/content_bundle_having_content.py
vdb_schema/content_core.py
vdb_schema/content_core_synopsis.py
vdb_schema/content_having_actor.py
vdb_schema/content_having_country.py
vdb_schema/content_having_director.py
vdb_schema/content_having_tag.py
vdb_schema/country.py
vdb_schema/customer.py
vdb_schema/gender.py
vdb_schema/hello_world.py
vdb_schema/homepage.py
vdb_schema/homepage_having_content.py
vdb_schema/package.py
vdb_schema/package_having_content_bundle.py
vdb_schema/paytv_provider.py
vdb_schema/product.py
vdb_schema/product_having_package.py
vdb_schema/season.py
vdb_schema/subcategory.py
vdb_schema/tags.py
vdb_schema/user_detail_having_package.py
vdb_schema/user_detail_having_product.py
vdb_schema/user_pay_tv.py
vdb_schema_module-0.2.1.dist-info/METADATA
vdb_schema_module-0.2.1.dist-info/WHEEL
vdb_schema_module-0.2.1.dist-info/top_level.txt
vdb_schema_module-0.2.1.dist-info/RECORD
