Metadata-Version: 2.1
Name: vdb-schema-module
Version: 0.2.1
Summary: Vdb schema models
Home-page: https://mnc-repo.mncdigital.com/ai-team/vision_plus/vdb_model_schema
Author: AI Teams
Author-email: ferdina.kusumah@mncgroup.com
License: MIT
Platform: UNKNOWN
Classifier: License :: OSI Approved :: MIT License
Classifier: Programming Language :: Python :: 3
Classifier: Programming Language :: Python :: 3.7
Classifier: Programming Language :: Python :: 3.8
Classifier: Programming Language :: Python :: 3.9
Requires-Dist: pydantic
